{"510":"PUBLIC POL FORMATION","513":"HEALTH DISPARITIES","521":"BASIC QUANT METHODS","525":"APP MULTIVAR METHODS","543":"ECONOMICS PUB POLICY","567":"BUDGETING/PP","596":"POLITICS OF POVERTY","612":"NONPROF COMM DEV FIN","630":"DISCRETE CHOICE MTHD","632":"COST/BENE ANALYSIS","634":"ML FOR PI","640":"POL RES PRAC I","641":"POL RES PRAC II","670":"DIRECTED STUDY","673":"APPLIED FIELD EXPER","684":"SEMINAR PUBLIC POLCY","685":"SEMINAR PUBLIC POLCY","686":"SEMINAR PUBLIC POLCY","688":"SEMINAR PUBLIC POLCY","690":"SEMINAR PUBLIC POLCY","800":"MATRIC CONTINUED","811":"GRADUATE FELLOWSHIP","822":"EAGLETON IND STUDY","866":"GRAD ASSISTANTSHIP","877":"TCHNG ASSISTANTSHIP"}