{"11:709:102":["QUICK, VIRGINIA"],"11:709:235":["ABBOT, JACLYN"],"11:709:255":["ABBOT, JACLYN","DIXON, JOSEPH"],"11:709:301":["PAPASPYROU, RAO"],"11:709:401":["ANTHONY, TRACY","MILLER, JOSHUA"],"11:709:403":["ANTHONY, TRACY","MILLER, JOSHUA"],"11:709:410":["QUICK, VIRGINIA"],"11:709:448":["PAPASPYROU, RAO"],"11:709:449":["PAPASPYROU, RAO"],"11:709:481":["WATFORD, MALCOLM"],"11:709:485":["SHAPSES, SUE"],"QUICK, VIRGINIA":["11:709:102","11:709:410"],"ABBOT, JACLYN":["11:709:235","11:709:255"],"DIXON, JOSEPH":["11:709:255"],"PAPASPYROU, RAO":["11:709:301","11:709:448","11:709:449"],"ANTHONY, TRACY":["11:709:401","11:709:403"],"MILLER, JOSHUA":["11:709:401","11:709:403"],"WATFORD, MALCOLM":["11:709:481"],"SHAPSES, SUE":["11:709:485"]}