{"220":["BRIGHTMAN, THERESA","OWENS, SHARON"],"322":["AMANO, TAKASHI","BRIGHTMAN, THERESA"],"333":["CHURCH, RUSLANA","ROGERS, KALEENA"],"341":["BIRD, JASON","REDDING, AUDREY"],"342":["EVERSMAN, MICHAEL"],"343":["MARTIN, MARY"],"345":["AMANO, TAKASHI","REDDING, AUDREY"],"346":["EVERSMAN, MICHAEL","REDDING, AUDREY"],"347":["WALTON, CLAYTON"],"412":["THOMPSON, WARREN","TOOMER, SHANELL"],"414":["CHURCH, RUSLANA","QUICK, KIM","ROGERS, KALEENA"],"467":["BIRD, JASON","CHURCH, RUSLANA","REDDING, AUDREY"],"468":["AMANO, TAKASHI","BIRD, JASON","CHURCH, RUSLANA","EVERSMAN, MICHAEL","REDDING, AUDREY"],"472":["CHURCH, RUSLANA","ROGERS, KALEENA"],"BRIGHTMAN, THERESA":["220","322"],"OWENS, SHARON":["220"],"AMANO, TAKASHI":["322","345","468"],"CHURCH, RUSLANA":["333","414","467","468","472"],"ROGERS, KALEENA":["333","414","472"],"BIRD, JASON":["341","467","468"],"REDDING, AUDREY":["341","345","346","467","468"],"EVERSMAN, MICHAEL":["342","346","468"],"MARTIN, MARY":["343"],"WALTON, CLAYTON":["347"],"THOMPSON, WARREN":["412"],"TOOMER, SHANELL":["412"],"QUICK, KIM":["414"]}