{"29:799:301":["AGRESTA, JOSEPH","IMPELLIZZERI, JOHN","MCLAURY, W","PEAVEY, HUSSAN"],"29:799:305":["COHEN, WARREN","HELLRIEGEL, JOHN","HELLRIEGEL, JOHN","IMPELLIZZERI, JOHN"],"29:799:310":["DREYFUS, DAVID","RODGERS, MARK"],"29:799:330":["COHEN, WARREN"],"29:799:380":["HERSZON, LEON","HERSZON, LEON","PALMON, NELLY","VOCATURO, JOSEPH"],"29:799:420":["AGRESTA, JOSEPH","PEAVEY, HUSSAN"],"29:799:440":["EASTMAN, WAYNE"],"29:799:455":["VISWANATHAN, ASHOK"],"29:799:460":["RODGERS, MARK"],"29:799:465":["ZHAO, YAO"],"29:799:476":["LYONS, KEVIN"],"29:799:491":["IMPELLIZZERI, JOHN"],"AGRESTA, JOSEPH":["29:799:301","29:799:420"],"IMPELLIZZERI, JOHN":["29:799:301","29:799:305","29:799:491"],"MCLAURY, W":["29:799:301"],"PEAVEY, HUSSAN":["29:799:301","29:799:420"],"COHEN, WARREN":["29:799:305","29:799:330"],"HELLRIEGEL, JOHN":["29:799:305","29:799:305"],"DREYFUS, DAVID":["29:799:310"],"RODGERS, MARK":["29:799:310","29:799:460"],"HERSZON, LEON":["29:799:380","29:799:380"],"PALMON, NELLY":["29:799:380"],"VOCATURO, JOSEPH":["29:799:380"],"EASTMAN, WAYNE":["29:799:440"],"VISWANATHAN, ASHOK":["29:799:455"],"ZHAO, YAO":["29:799:465"],"LYONS, KEVIN":["29:799:476"]}