{"101":["DREFF, ERIK","LORUSSO, JAMES","WASSERMAN, EMMA"],"105":["KOLBABA, TIA","WILLIAMS, JOSEPH"],"111":["RUSSEL-JONES, SANDRA"],"206":["YADIN-ISRAEL, AZZAN"],"212":["LORUSSO, JAMES","PAVLIN, JAMES"],"222":["MCGINLEY, DUGAN"],"226":["MOJADDEDI, JAWID"],"233":["MCGINLEY, DUGAN"],"293":["KOLBABA, TIA"],"305":["KETCHUM, MATTHEW"],"311":["FRUCHTMAN, DIANE"],"333":["SUROWITZ, HILIT"],"372":["MOJADDEDI, JAWID"],"426":["FRUCHTMAN, DIANE"],"DREFF, ERIK":["101"],"LORUSSO, JAMES":["101","212"],"WASSERMAN, EMMA":["101"],"KOLBABA, TIA":["105","293"],"WILLIAMS, JOSEPH":["105"],"RUSSEL-JONES, SANDRA":["111"],"YADIN-ISRAEL, AZZAN":["206"],"PAVLIN, JAMES":["212"],"MCGINLEY, DUGAN":["222","233"],"MOJADDEDI, JAWID":["226","372"],"KETCHUM, MATTHEW":["305"],"FRUCHTMAN, DIANE":["311","426"],"SUROWITZ, HILIT":["333"]}