{"502":"THER FNC REAL VAR II","504":"THER FNC COMP VAR II","508":"FUNCTIONAL ANALYS II","510":"TOPICS IN ANALYSIS","518":"PARTL DIFF EQUATN II","534":"SEL TPCS GEOMETRY I","537":"SEL TPCS GEOMETRY II","541":"INTR ALG TOPOLOGY II","547":"TOPOLOGY MANIFOLDS","550":"LIE ALGEBRAS","552":"ABSTRACT ALGEBRA II","557":"VERT OPERATOR ALGEBR","566":"AXIOMATIC SET THEORY","572":"NUMBER THEORY II","573":"SPEC TOP NUMBER THRY","601":"MATH TA TRAIN","615":"SPEC STDY ADV MATH","617":"SEMINAR IN MATH II","702":"RES IN MATHEMATICS","800":"MATRICULATION CONTD","811":"GRADUATE FELLOWSHIP","855":"GRADUATE TRAINEESHIP","866":"FULL GA APPOINTMENT","867":"PART GA APPOINTMENT","877":"FULL TA APPOINTMENT","878":"PART TA APPOINTMENT"}