{"16:635:503":["AKDOGAN, ENVER"],"16:635:506":["GOEL, ASHUTOSH"],"16:635:516":["GAROFALINI, STEPHEN"],"16:635:524":["MILLER, STEVE"],"16:635:528":["BIRNIE, DUNBAR"],"16:635:532":["KLEIN, LISA"],"16:635:602":["O'CARROLL, DEIRDRE"],"16:635:604":["O'CARROLL, DEIRDRE","RAMACHANDRAN, ROHIT"],"16:635:702":["AKDOGAN, ENVER","BIRNIE, DUNBAR","FABRIS","GAROFALINI, STEPHEN","GOEL, ASHUTOSH","KLEIN, LISA","MANN, ADRIAN","O'CARROLL, DEIRDRE","RIMAN, RICHARD","SAFARI, AHMAD","SILLS, RYAN","TSAKALAKOS"],"16:635:800":["O'CARROLL, DEIRDRE"],"16:635:811":["O'CARROLL, DEIRDRE"],"16:635:844":["O'CARROLL, DEIRDRE"],"16:635:866":["O'CARROLL, DEIRDRE"],"16:635:877":["O'CARROLL, DEIRDRE"],"AKDOGAN, ENVER":["16:635:503","16:635:702"],"GOEL, ASHUTOSH":["16:635:506","16:635:702"],"GAROFALINI, STEPHEN":["16:635:516","16:635:702"],"MILLER, STEVE":["16:635:524"],"BIRNIE, DUNBAR":["16:635:528","16:635:702"],"KLEIN, LISA":["16:635:532","16:635:702"],"O'CARROLL, DEIRDRE":["16:635:602","16:635:604","16:635:702","16:635:800","16:635:811","16:635:844","16:635:866","16:635:877"],"RAMACHANDRAN, ROHIT":["16:635:604"],"FABRIS":["16:635:702"],"MANN, ADRIAN":["16:635:702"],"RIMAN, RICHARD":["16:635:702"],"SAFARI, AHMAD":["16:635:702"],"SILLS, RYAN":["16:635:702"],"TSAKALAKOS":["16:635:702"]}